{
  "metadata": {
    "version": "2.0",
    "last_updated": "2025-11-09",
    "total_companies": 62,
    "source": "AGENT-R01 Industry Mapping Report + AGENT-R02 Financial Intelligence Report",
    "confidence_methodology": "0.95-1.0: SEC verified | 0.90-0.94: DOE grants/major press | 0.85-0.89: State govt/trade press | 0.80-0.84: Company websites"
  },
  "publicCompanies": [
    {
      "id": 1,
      "name": "Tesla Inc.",
      "ticker": "TSLA",
      "exchange": "NASDAQ",
      "headquarters": "Austin, Texas",
      "founded": 2003,
      "technology": "4680 and 2170 cylindrical lithium-ion batteries",
      "stage": "Scaled commercial (gigafactory leader)",
      "capacity_gwh": 100,
      "capacity_target": {"2025": "100+ GWh"},
      "employees": 140473,
      "facilities": [
        {"name": "Gigafactory Texas", "location": "Austin, TX", "capacity_gwh": 40, "status": "Operating", "products": ["4680 cells"]},
        {"name": "Gigafactory Nevada", "location": "Sparks, NV", "capacity_gwh": 100, "status": "Operating (with Panasonic)", "products": ["2170 cells", "4680 cells"]}
      ],
      "partnerships": ["Panasonic", "LG Energy Solution"],
      "funding": {
        "ipo_date": "2010-06-29",
        "ipo_price": "$17.00",
        "total_raised_pre_profitability": "$13.4B",
        "doe_atvm_loan": "$465M (repaid 2013)"
      },
      "financials": {
        "2024_revenue": "$97.7B",
        "2023_revenue": "$96.8B",
        "2024_net_income": "$7.1B",
        "2023_net_income": "$15.0B",
        "cash_position": "$36.5B",
        "total_debt": "$19.5B",
        "net_cash": "$17.0B",
        "capex_2024": "$11.3B"
      },
      "institutional_ownership": {
        "percentage": 46,
        "top_holders": [
          {"name": "Vanguard Group", "shares_millions": 239.62, "percentage": 7.43},
          {"name": "BlackRock", "shares_millions": 194.74, "percentage": 6.04},
          {"name": "State Street", "shares_millions": 113.73, "percentage": 3.53}
        ]
      },
      "products": ["4680 battery cells", "2170 battery cells", "Megapack", "Powerwall"],
      "milestones": [
        {"year": 2024, "event": "100 million 4680 cells produced (September)"},
        {"year": 2010, "event": "IPO - first US automaker since Ford (1956)"}
      ],
      "competitive_advantages": ["Vertical integration", "Scale (100+ GWh)", "4680 cell innovation", "$17B net cash"],
      "risk_factors": ["Competition intensifying", "Price cuts eroding margins", "Profitability declined 53% YoY (2024)"],
      "confidence_score": 1.0
    },
    {
      "id": 2,
      "name": "QuantumScape Corporation",
      "ticker": "QS",
      "exchange": "NYSE",
      "headquarters": "San Jose, CA",
      "founded": 2010,
      "technology": "Solid-state lithium-metal battery",
      "stage": "Pre-commercial (development/pilot)",
      "capacity_gwh": null,
      "employees": 800,
      "partnerships": ["PowerCo (Volkswagen)"],
      "funding": {
        "total_raised": "$1.5B+",
        "ipo_date": "2020-11-25",
        "ipo_method": "SPAC (Kensington Capital)",
        "valuation": "$3.3B (at IPO)",
        "volkswagen_investment": "$531M+ (cumulative through 2025)"
      },
      "financials": {
        "2024_revenue": "$0M",
        "2024_net_loss": "$477.9M",
        "2023_net_loss": "$445M",
        "rd_spending_2024": "$383M",
        "cash_position": "$900M",
        "burn_rate_quarterly": "$120M",
        "cash_runway": "Through H2 2028"
      },
      "institutional_ownership": {
        "percentage": 27.21,
        "insider_ownership": 39.23,
        "top_holders": [
          {"name": "Volkswagen Group", "shares_millions": 68.24, "percentage": 12.21},
          {"name": "Vanguard Group", "shares_millions": 32.44, "percentage": 5.93},
          {"name": "BlackRock", "shares_millions": 15.57, "percentage": 2.85}
        ]
      },
      "products": ["QSE-5 solid-state battery"],
      "milestones": [
        {"year": 2024, "event": "PowerCo (VW) licensing agreement (July)"},
        {"year": 2024, "event": "B-samples delivered to VW (October)"},
        {"year": 2020, "event": "SPAC merger completed"}
      ],
      "competitive_advantages": ["Volkswagen strategic partnership ($531M)", "Solid-state technology leader", "Strong IP portfolio"],
      "risk_factors": ["Pre-revenue after 14 years", "Burn rate $478M/year", "Commercialization timeline uncertain", "6-8 quarter cash runway"],
      "confidence_score": 0.98
    },
    {
      "id": 3,
      "name": "Amprius Technologies",
      "ticker": "AMPX",
      "exchange": "NASDAQ",
      "headquarters": "Fremont, CA",
      "founded": 2008,
      "technology": "Silicon anode lithium-ion batteries (NOT solid-state)",
      "stage": "Commercial production",
      "capacity_gwh": 5,
      "capacity_target_year": 2028,
      "employees": 250,
      "partnerships": [],
      "funding": {
        "total_raised": "$500M+",
        "ipo_date": "2022",
        "ipo_method": "SPAC"
      },
      "financials": {
        "2024_revenue": "$24.2M",
        "2023_revenue": "$8.8M",
        "revenue_growth_yoy": "175%",
        "2024_net_loss": "$44.7M",
        "cash_position": "$70M",
        "burn_rate_quarterly": "$11M",
        "cash_runway": "6 quarters"
      },
      "institutional_ownership": {
        "percentage": 7.81,
        "private_company_control": 59,
        "retail_ownership": 83.85
      },
      "products": ["Ultra-high energy density Li-ion for mobility"],
      "features": ["Higher energy density vs graphite anode", "Faster charging"],
      "applications": ["Aerospace", "Defense", "Premium automotive"],
      "competitive_advantages": ["Silicon anode technology", "Revenue growth 175% YoY", "Aerospace/defense customers"],
      "risk_factors": ["Minimal institutional ownership (7.81%)", "59% private company control limits liquidity", "6-quarter runway", "Needs refinancing"],
      "confidence_score": 0.98
    },
    {
      "id": 4,
      "name": "FREYR Battery",
      "ticker": "FREY",
      "exchange": "NYSE",
      "headquarters": "Georgia (redomiciled from Luxembourg 2023)",
      "founded": 2018,
      "technology": "Lithium iron phosphate (LFP) using 24M SemiSolid platform",
      "stage": "Pilot to commercial transition",
      "capacity_gwh": 50,
      "capacity_target": {"2025": 50, "2030": 200},
      "employees": 400,
      "facilities": [
        {"name": "CQP Pilot", "location": "Mo I Rana, Norway", "capacity_gwh": 0.5},
        {"name": "Giga America", "location": "Coweta County, Georgia", "capacity_gwh": 50, "status": "Construction deferred"}
      ],
      "partnerships": ["24M Technologies (tech license)"],
      "funding": {
        "total_raised": "$800M+",
        "ipo_date": "2021-07-09",
        "ipo_method": "SPAC (Alussa Energy Acquisition)",
        "pipe_investors": ["Koch Strategic Platforms", "Glencore", "Fidelity", "Franklin Templeton"],
        "actual_proceeds": "$704M (post-redemptions)",
        "off_take_agreements": "$3B"
      },
      "financials": {
        "2024_revenue": "$0M",
        "q3_2024_net_loss": "$27.5M",
        "q3_2023_net_loss": "$9.8M",
        "cash_q3_2024": "$184.1M",
        "burn_rate_quarterly": "$27M",
        "cash_runway": "6-7 quarters"
      },
      "institutional_ownership": {
        "percentage": 40.71,
        "top_holders": [
          {"name": "Sylebra HK", "shares_millions": 15, "percentage": 10.70},
          {"name": "Encompass Capital", "shares_millions": 13.46, "percentage": 9.58},
          {"name": "Spring Creek Capital", "shares_millions": 11.5, "percentage": 8.20}
        ]
      },
      "products": ["LFP battery cells", "LFP battery modules"],
      "competitive_advantages": ["24M SemiSolid technology", "$3B off-take agreements", "US redomiciliation (DOE loan eligible)"],
      "risk_factors": ["Pre-revenue", "Burn tripled (Q3 '23: $9.8M → Q3 '24: $27.5M)", "Giga America construction deferred", "6-7 quarter runway"],
      "confidence_score": 0.94
    },
    {
      "id": 5,
      "name": "Eos Energy Enterprises",
      "ticker": "EOSE",
      "exchange": "NASDAQ",
      "headquarters": "Edison, New Jersey",
      "founded": 2008,
      "technology": "Znyth aqueous zinc battery (non-lithium)",
      "stage": "Commercial production",
      "capacity_gwh": 8,
      "capacity_target_year": 2027,
      "employees": 300,
      "facilities": [
        {"name": "Project AMAZE", "location": "Pennsylvania", "capacity_gwh": 8}
      ],
      "partnerships": [],
      "funding": {
        "total_raised": "$600M+",
        "ipo_date": "2020-11-16",
        "ipo_method": "SPAC (B. Riley Principal Merger Corp. II)",
        "pipe_backing": "$50M (B. Riley backstop)",
        "doe_loan": "$303.5M (closed December 2024)"
      },
      "financials": {
        "2024_revenue": "$15.6M",
        "2023_revenue": "$16.4M",
        "2024_net_loss": "$268M",
        "2024_adj_ebitda_loss": "$44.6M",
        "cash_12_31_2023": "$69.5M",
        "burn_rate_quarterly": "$11M (Adj EBITDA)",
        "cash_runway": "6 quarters"
      },
      "institutional_ownership": {
        "percentage": "30-65% (conflicting sources)",
        "strategic_investors": ["Cerberus Capital Management (distressed specialist)"]
      },
      "products": ["Z3 DC battery system", "Grid-scale energy storage"],
      "features": ["4-12 hour duration", "Aqueous zinc chemistry", "Non-flammable"],
      "competitive_advantages": ["$303.5M DOE loan (closed)", "Aqueous zinc safety", "Grid-scale focus"],
      "risk_factors": ["Revenue declining (-13.3% CAGR)", "Cerberus involvement = restructuring risk", "6-quarter runway", "$303.5M loan critical to survival"],
      "confidence_score": 0.95
    },
    {
      "id": 6,
      "name": "Fluence Energy",
      "ticker": "FLNC",
      "exchange": "NYSE",
      "headquarters": "Arlington, Virginia",
      "founded": 2018,
      "technology": "Integrated battery energy storage systems (BESS)",
      "stage": "Scaled commercial",
      "deployed_capacity_gw": 5.0,
      "markets": 33,
      "countries": 25,
      "employees": 800,
      "facilities": [
        {"name": "Utah Module Production", "location": "Utah", "start_date": "September 2024"}
      ],
      "partnerships": ["Siemens (parent)", "AES (parent)"],
      "funding": {
        "ipo_date": "2021",
        "parent_companies": "Siemens/AES joint venture"
      },
      "financials": {
        "2024_revenue": "$2.8B",
        "2024_net_income": "$120M"
      },
      "products": ["Gridstack Pro", "Gridstack", "Sunstack", "Edgestack", "Ultrastack"],
      "competitive_advantages": ["5 GW deployed globally", "Siemens/AES backing", "33 markets", "Profitable ($120M net income)"],
      "risk_factors": ["Dependent on battery cell suppliers", "Project execution risk"],
      "confidence_score": 0.98
    },
    {
      "id": 7,
      "name": "Clearway Energy",
      "ticker": "CWEN",
      "exchange": "NYSE",
      "headquarters": "Princeton, New Jersey",
      "founded": 2012,
      "technology": "Solar + battery energy storage systems (BESS)",
      "stage": "Commercial deployment",
      "capacity_gwh": 11.8,
      "capacity_breakdown": "9 GW wind/solar/BESS, 2.8 GW dispatchable",
      "employees": null,
      "facilities": null,
      "projects": ["Victory Pass", "Arica", "Daggett 1 BESS", "Honeycomb Portfolio", "Pine Forest", "Rosamond South I"],
      "funding": {},
      "financials": {
        "2024_revenue": "$1,371M",
        "revenue_source": "SEC 10-Q filings"
      },
      "products": ["Solar+storage projects", "Wind+storage projects"],
      "competitive_advantages": ["11.8 GW gross capacity", "Diversified renewable portfolio", "Stable revenue model"],
      "risk_factors": ["Commodity price exposure", "Regulatory/policy changes"],
      "confidence_score": 0.96
    },
    {
      "id": 8,
      "name": "ESS Tech Inc.",
      "ticker": "GWH",
      "exchange": "NYSE",
      "headquarters": "Wilsonville, Oregon",
      "founded": 2011,
      "technology": "Iron flow battery",
      "stage": "Commercial production",
      "employees": null,
      "products": ["Energy Warehouse", "Energy Center", "Energy Base"],
      "chemistry": "Iron, salt, and water electrolyte",
      "duration": "4-12 hours energy storage",
      "funding": {
        "ipo_date": "2021-10",
        "ipo_method": "SPAC (Acon S2)"
      },
      "competitive_advantages": ["Non-toxic chemistry", "Long duration storage", "Unlimited cycling"],
      "risk_factors": ["Energy density lower than lithium-ion", "Early commercialization"],
      "confidence_score": 0.97
    },
    {
      "id": 9,
      "name": "Energy Vault Holdings",
      "ticker": "NRGV",
      "exchange": "NYSE",
      "headquarters": "Westlake Village, California",
      "founded": null,
      "technology": "Gravity, battery, and hydrogen energy storage",
      "stage": "Commercial deployment",
      "capacity_pipeline_gw": 1.5,
      "products": ["G-Vault (gravity)", "B-Vault (electrochemical)", "H-Vault (hydrogen)", "Vault-OS software"],
      "funding": {
        "ipo_date": "2022-02",
        "recent_funding": "$300M preferred equity (Asset Vault subsidiary)"
      },
      "competitive_advantages": ["Multi-technology platform", "$300M recent funding", "1.5 GW pipeline"],
      "risk_factors": ["Gravity storage unproven at scale", "Multiple technology focus = dilution"],
      "confidence_score": 0.95
    },
    {
      "id": 10,
      "name": "Stem Inc.",
      "ticker": "STEM",
      "exchange": "NYSE",
      "headquarters": "Millbrae, California",
      "founded": null,
      "technology": "AI-driven energy storage optimization software",
      "stage": "Commercial - pivot to software/services",
      "products": ["PowerTrack Optimizer (formerly Athena)"],
      "business_model": "Energy storage and solar software/services",
      "funding": {
        "ipo_date": "2021-04",
        "ipo_method": "SPAC (Star Peak)"
      },
      "competitive_advantages": ["Software-focused (asset-light)", "AI optimization", "Recurring revenue model"],
      "risk_factors": ["Software competition", "Dependent on energy storage adoption"],
      "confidence_score": 0.98
    },
    {
      "id": 11,
      "name": "Sunrun Inc.",
      "ticker": "RUN",
      "exchange": "NASDAQ",
      "headquarters": "San Francisco, California",
      "founded": 2007,
      "technology": "Residential solar + battery storage (subscription model)",
      "stage": "Scaled commercial",
      "employees": null,
      "california_storage_attachment": "85-90%",
      "virtual_power_plant": "CalReady (250 MW output capability)",
      "funding": {},
      "acquisitions": [
        {"company": "Vivint Solar", "amount": "$3.2B", "year": 2020}
      ],
      "competitive_advantages": ["Largest residential installer", "CalReady VPP (250 MW)", "Vivint acquisition scale"],
      "risk_factors": ["NEM 3.0 policy headwinds", "Interest rate sensitivity"],
      "confidence_score": 0.99
    },
    {
      "id": 12,
      "name": "Solid Power Inc.",
      "ticker": "SLDP",
      "exchange": "NASDAQ",
      "headquarters": "Louisville, Colorado",
      "founded": 2011,
      "technology": "Sulfide-based solid electrolyte for all-solid-state batteries",
      "stage": "Development/pilot production",
      "capacity_gwh": null,
      "employees": 250,
      "partnerships": ["BMW", "Ford"],
      "funding": {
        "total_raised": "$542.9M",
        "ipo_date": "2021-12",
        "ipo_method": "SPAC with DCRC"
      },
      "financials": {
        "2024_revenue": "$12M",
        "2024_net_loss": "$78M"
      },
      "products": ["Sulfide solid electrolyte", "B-samples to OEMs"],
      "timeline": [
        {"year": 2030, "event": "Commercial production target"}
      ],
      "competitive_advantages": ["BMW + Ford partnerships", "Sulfide solid-state tech"],
      "risk_factors": ["2030 commercialization target = long runway", "Minimal revenue ($12M)"],
      "confidence_score": 0.97
    },
    {
      "id": 13,
      "name": "Microvast Holdings",
      "ticker": "MVST",
      "exchange": "NASDAQ",
      "headquarters": "Stafford, Texas",
      "founded": 2006,
      "technology": "Lithium-ion batteries with polyaramid separator",
      "stage": "Commercial production",
      "capacity_gwh": 15,
      "employees": 2000,
      "facilities": [
        {"name": "Clarksville", "location": "Tennessee", "capacity_gwh": 6},
        {"name": "Florida Facility", "location": "Florida", "capacity_gwh": 3},
        {"name": "Colorado Facility", "location": "Colorado", "capacity_gwh": 3},
        {"name": "Texas Facility", "location": "Texas", "capacity_gwh": 3}
      ],
      "vertical_integration": ["Cathode", "Anode", "Electrolyte", "Separator", "Modules", "Packs"],
      "funding": {
        "total_raised": "$400M+",
        "doe_grant": "$200M (later withdrawn)"
      },
      "financials": {
        "2024_revenue": "$180M",
        "2024_net_loss": "$65M"
      },
      "competitive_advantages": ["Vertical integration", "15 GWh capacity", "Multiple US facilities"],
      "risk_factors": ["DOE grant withdrawn", "Ongoing losses despite scale"],
      "confidence_score": 0.96
    },
    {
      "id": 14,
      "name": "Enphase Energy",
      "ticker": "ENPH",
      "exchange": "NASDAQ",
      "headquarters": "Fremont, California",
      "founded": 2006,
      "technology": "IQ Battery (lithium iron phosphate - LFP) residential storage",
      "stage": "Commercial scaled production",
      "capacity_gwh": 5,
      "employees": 3500,
      "products": ["IQ Battery 10", "IQ Battery 10C (US domestic content)", "IQ Battery 10T"],
      "features": ["10 kWh usable per unit", "Cobalt-free LFP"],
      "funding": {
        "ipo_date": "2012"
      },
      "financials": {
        "2024_revenue": "$2.3B",
        "2024_net_income": "$340M"
      },
      "competitive_advantages": ["Profitable ($340M)", "LFP chemistry", "US domestic content"],
      "risk_factors": ["Residential market headwinds", "NEM 3.0 impact"],
      "confidence_score": 0.97
    },
    {
      "id": 15,
      "name": "Albemarle Corporation",
      "ticker": "ALB",
      "exchange": "NYSE",
      "headquarters": "Charlotte, North Carolina",
      "founded": 1994,
      "technology": "Lithium mining and refining",
      "stage": "Commercial",
      "operations": [
        {"name": "Silver Peak", "location": "Nevada", "status": "Only active US lithium mine"},
        {"name": "Kings Mountain", "location": "North Carolina", "status": "Planned reopening"}
      ],
      "ranking": "4th largest lithium producer globally",
      "employees": 7900,
      "funding": {},
      "financials": {
        "2024_revenue": "$6.2B",
        "2024_net_income": "$1.1B"
      },
      "competitive_advantages": ["Only active US lithium mine", "Kings Mountain expansion", "Global scale"],
      "risk_factors": ["Lithium price volatility", "International competition"],
      "confidence_score": 0.99
    },
    {
      "id": 16,
      "name": "Livent Corporation",
      "ticker": "LTHM",
      "exchange": "NYSE",
      "headquarters": "Philadelphia, Pennsylvania",
      "founded": 2018,
      "technology": "Lithium hydroxide and carbonate production",
      "stage": "Commercial",
      "capacity_tonnes": 40000,
      "employees": 1100,
      "funding": {},
      "financials": {
        "2024_revenue": "$850M",
        "2024_net_income": "$180M"
      },
      "competitive_advantages": ["High-purity lithium", "40K tonnes capacity", "Profitable"],
      "risk_factors": ["Lithium price exposure", "Smaller scale vs Albemarle"],
      "confidence_score": 0.98
    },
    {
      "id": 17,
      "name": "Piedmont Lithium",
      "ticker": "PLL",
      "exchange": "NASDAQ",
      "headquarters": "Belmont, North Carolina",
      "founded": null,
      "technology": "Lithium mining (hard rock deposit)",
      "stage": "Development (pre-revenue)",
      "location": "30 miles west of Charlotte, NC",
      "projects": ["North Carolina", "Tennessee", "Canada", "Ghana"],
      "competitive_advantages": ["US domestic lithium source", "Multiple project pipeline"],
      "risk_factors": ["Pre-revenue", "Permitting delays", "Capital intensity"],
      "confidence_score": 0.93
    },
    {
      "id": 18,
      "name": "American Battery Technology Company",
      "ticker": "ABAT",
      "exchange": "NASDAQ",
      "headquarters": "Reno, Nevada",
      "founded": null,
      "technology": "Lithium-ion battery recycling, critical materials extraction",
      "stage": "Pilot production",
      "facility": "McCarran, Nevada (EPA-approved under CERCLA)",
      "employees": null,
      "funding": {
        "doe_grants": "$20M DOE project + $2M U.S. ABC grant"
      },
      "financials": {
        "2024_revenue": "$0.9M",
        "2023_revenue": "$0.2M"
      },
      "major_projects": [
        {
          "name": "Moss Landing BESS cleanup",
          "partner": "Veolia",
          "scope": "Up to 100,000 Li-ion modules",
          "significance": "Largest US battery cleanup",
          "epa_contract": true
        }
      ],
      "competitive_advantages": ["EPA-approved facility", "Moss Landing contract (100K modules)", "$22M DOE grants"],
      "risk_factors": ["Minimal revenue ($0.9M)", "Early stage recycling technology"],
      "confidence_score": 0.97
    },
    {
      "id": 19,
      "name": "Li-Cycle Holdings",
      "ticker": "LICY",
      "exchange": "NYSE",
      "headquarters": "Rochester, New York (parent: Toronto)",
      "founded": 2016,
      "technology": "Spoke-and-hub battery recycling model",
      "stage": "Commercial (Rochester hub paused)",
      "facilities": [
        {"name": "Rochester Hub", "location": "New York", "status": "Under construction (paused)"},
        {"name": "Gilbert Spoke", "location": "Arizona", "status": "Operating"},
        {"name": "Tuscaloosa Spoke", "location": "Alabama", "status": "Operating"}
      ],
      "funding": {
        "ipo_date": "2021-08",
        "ipo_method": "SPAC",
        "doe_loan": "$375M conditional (Rochester hub)"
      },
      "status_change": "Operations transferred to Glencore Battery Recycling (GBR)",
      "competitive_advantages": ["Spoke-and-hub model", "$375M DOE loan approved", "Glencore partnership"],
      "risk_factors": ["Rochester hub paused", "Glencore takeover = loss of independence"],
      "confidence_score": 0.90
    },
    {
      "id": 20,
      "name": "Nikola Corporation",
      "ticker": "NKLA",
      "exchange": "NASDAQ",
      "headquarters": "Phoenix, Arizona",
      "founded": null,
      "technology": "Battery pack manufacturing for electric trucks",
      "stage": "Commercial (restructured)",
      "acquisition": {
        "company": "Romeo Power",
        "amount": "$144M",
        "date": "2022-08",
        "outcome": "Liquidated, transferred to SG Service Co. LLC"
      },
      "facility": "Battery manufacturing in Coolidge, Arizona",
      "competitive_advantages": ["Electric truck focus"],
      "risk_factors": ["Romeo Power liquidation", "Electric truck market challenges"],
      "confidence_score": 0.96
    },
    {
      "id": 21,
      "name": "SunPower Corporation",
      "ticker": "SPWR",
      "exchange": "NASDAQ",
      "headquarters": "Richmond, California",
      "founded": null,
      "technology": "Solar + battery storage (residential/commercial)",
      "stage": "BANKRUPT",
      "status": "Chapter 11 bankruptcy (August 2024)",
      "cause": "NEM 3.0 policy impact, accounting issues, high interest rates",
      "historical_peak": "$9B valuation (2021)",
      "asset_sale": "Complete Solaria acquired Blue Raven Solar for $45M",
      "competitive_advantages": "None (bankrupt)",
      "risk_factors": "Bankruptcy = total loss",
      "confidence_score": 0.95
    },
    {
      "id": 22,
      "name": "Ultralife Corporation",
      "ticker": "ULBI",
      "exchange": "NASDAQ",
      "headquarters": "Newark, New York",
      "founded": null,
      "technology": "Primary lithium and rechargeable batteries",
      "stage": "Commercial",
      "markets": ["Military", "Medical", "Industrial"],
      "sic_code": "3691",
      "competitive_advantages": ["Military/medical specialization", "Primary lithium expertise"],
      "risk_factors": ["Niche markets", "Limited growth"],
      "confidence_score": 0.93
    },
    {
      "id": 23,
      "name": "Energizer Holdings",
      "ticker": "ENR",
      "exchange": "NYSE",
      "headquarters": "St. Louis, Missouri",
      "founded": null,
      "technology": "Primary and rechargeable batteries (consumer)",
      "stage": "Commercial scaled",
      "brands": ["Energizer", "Rayovac", "VARTA Consumer"],
      "sic_code": "3692",
      "competitive_advantages": ["Brand recognition", "Global distribution", "Consumer market leader"],
      "risk_factors": ["Commodity battery market", "Rechargeable competition"],
      "confidence_score": 0.98
    },
    {
      "id": 24,
      "name": "EnerSys",
      "ticker": "ENS",
      "exchange": "NYSE",
      "headquarters": "Reading, Pennsylvania",
      "founded": null,
      "technology": "Lead-acid and lithium batteries for industrial applications",
      "stage": "Commercial scaled",
      "markets": ["Motive power", "Reserve power", "Specialty"],
      "sic_code": "3691",
      "competitive_advantages": ["Industrial focus", "Dual technology (lead-acid + lithium)", "Global scale"],
      "risk_factors": ["Lead-acid market maturity", "Lithium competition"],
      "confidence_score": 0.96
    },
    {
      "id": 25,
      "name": "SolarEdge Technologies",
      "ticker": "SEDG",
      "exchange": "NASDAQ",
      "headquarters": "Herzliya, Israel",
      "founded": null,
      "technology": "SolarEdge Home Battery (DC-coupled, 9.7 kWh)",
      "stage": "Commercial",
      "products": ["Lithium-ion battery storage for residential solar"],
      "competitor": "Tesla Powerwall",
      "competitive_advantages": ["DC-coupled efficiency", "Solar integration"],
      "risk_factors": ["Residential solar headwinds", "Tesla competition"],
      "confidence_score": 0.96
    }
  ],
  "privateCompanies": [
    {
      "id": 101,
      "name": "Redwood Materials",
      "headquarters": "Carson City, Nevada",
      "founded": 2017,
      "founder": "JB Straubel (Tesla co-founder/former CTO)",
      "technology": "Hydrometallurgical recycling + cathode production",
      "stage": "Commercial",
      "capacity_target": {"2030": "100 GWh cathode materials"},
      "employees": 600,
      "facilities": [
        {"name": "Carson City Recycling", "location": "Nevada", "investment": "$3.5B", "status": "Operating"},
        {"name": "South Carolina Cathode", "location": "South Carolina", "status": "Planned"}
      ],
      "funding": {
        "total_raised": "$2B+ equity",
        "valuation": "$5B (2023)",
        "doe_atvm_loan": "$2B conditional (February 2023)",
        "investors": ["T. Rowe Price", "Panasonic", "Amazon Climate Pledge Fund"]
      },
      "recovery_rates": "95-98% nickel/copper/cobalt, 80%+ lithium",
      "timeline": [
        {"year": 2017, "event": "Founded by JB Straubel"},
        {"year": 2021, "event": "Raised $700M Series C"},
        {"year": 2023, "event": "$2B DOE ATVM loan + South Carolina facility announced"}
      ],
      "competitive_advantages": ["JB Straubel (Tesla pedigree)", "$2B DOE loan", "95-98% recovery rates", "Anode copper foil production"],
      "risk_factors": ["Dependent on EV battery volume", "DOE loan conditional"],
      "confidence_score": 0.98
    },
    {
      "id": 102,
      "name": "Sila Nanotechnologies",
      "headquarters": "Alameda, California",
      "founded": 2011,
      "technology": "Silicon-composite anode materials (Titan Silicon)",
      "stage": "Commercial (Mercedes EQG 2023)",
      "capacity_target": {"2028": "Materials for 1M+ vehicles/year"},
      "employees": 500,
      "facility": "Moses Lake, WA (600,000+ sq ft)",
      "funding": {
        "total_raised": "$1.1B+",
        "latest_round": "Series G - $375M (June 2024)",
        "doe_grant": "$100M (October 2022)",
        "investors": ["Daimler", "Sutter Hill Ventures", "In-Q-Tel"]
      },
      "products": ["Titan Silicon anode material"],
      "partnerships": ["Mercedes-Benz", "Panasonic", "ATL", "+3 undisclosed"],
      "features": ["20% higher energy density", "Drop-in replacement for graphite"],
      "production_start": "Q4 2025",
      "competitive_advantages": ["Mercedes production (2023)", "$1.1B funding", "100+ GWh capacity planned", "$100M DOE grant"],
      "risk_factors": ["Silicon anode durability", "Manufacturing scale-up"],
      "confidence_score": 0.97
    },
    {
      "id": 103,
      "name": "Form Energy",
      "headquarters": "Somerville, Massachusetts",
      "founded": 2017,
      "founders": ["Mateo Jaramillo (ex-Tesla)", "Yet-Ming Chiang (MIT)", "Ted Wiley", "William Woodford", "Marco Ferrara"],
      "technology": "Iron-air battery (100-hour duration)",
      "stage": "Pilot-to-commercial transition",
      "cost_target": "$20/kWh LCOS",
      "employees": 350,
      "facilities": [
        {"name": "Weirton Factory", "location": "West Virginia", "capacity": "Iron-air battery production"}
      ],
      "funding": {
        "total_raised": "$800M+",
        "latest_round": "Series F - $405M (2024) led by GE Vernova, Breakthrough Energy Ventures",
        "doe_support": "$147M BEAD grant + $760M conditional loan"
      },
      "major_projects": [
        {"name": "Lincoln, Maine", "capacity_mw": 85, "federal_grant": "$147M"}
      ],
      "partners": ["ArcelorMittal (steel)", "Multiple utilities"],
      "products": ["100-hour iron-air battery"],
      "features": ["<$20/kWh LCOS", "Multi-day storage", "Non-flammable"],
      "competitive_advantages": ["100-hour duration (longest)", "$800M+ funding", "$760M DOE loan conditional", "GE Vernova partnership"],
      "risk_factors": ["Unproven technology at scale", "2026 production target"],
      "confidence_score": 0.96
    },
    {
      "id": 104,
      "name": "Group14 Technologies",
      "headquarters": "Woodinville, Washington",
      "founded": 2015,
      "technology": "SCC55 silicon-carbon composite for anodes",
      "stage": "Pilot to commercial",
      "performance": "50% longer battery life",
      "employees": null,
      "facilities": [
        {"name": "BAM-2", "location": "Moses Lake, WA", "size_sqft": "1 million", "status": "Production late 2024"}
      ],
      "funding": {
        "total_raised": "$1B+",
        "latest_round": "Series D - $463M (August 2025) - SK Inc., Porsche, ATL, OMERS, Microsoft Climate Innovation Fund",
        "previous_round": "Series C - $614M (Porsche, Microsoft)",
        "doe_grant": "$100M"
      },
      "production_start": "Late 2024",
      "competitive_advantages": ["$1B+ funding", "Porsche + Microsoft + SK backing", "1M sq ft facility", "$100M DOE grant"],
      "risk_factors": ["Silicon-carbon durability", "Manufacturing yield"],
      "confidence_score": 0.97
    },
    {
      "id": 105,
      "name": "Our Next Energy (ONE)",
      "headquarters": "Novi, Michigan (Van Buren Township facility)",
      "founded": 2020,
      "founder": "Mujeeb Ijaz (30+ years battery experience, former A123 Systems)",
      "technology": "Gemini Dual-Chemistry battery (LFP + range extender)",
      "stage": "Development/pilot",
      "specifications": "185 kWh, 600 miles range",
      "capacity_target_gwh": 20,
      "employees": null,
      "jobs_created": 2112,
      "funding": {
        "total_investment": "$1.6B",
        "state_support": "$236.6M ($200M SOAR grant + $15M loan)",
        "bmw_series_a": "$25M (2021)",
        "bmw_series_b": "$65M (2022)",
        "partners": ["BMW i Ventures", "Amazon Climate Pledge Fund"]
      },
      "milestones": [
        {"year": 2022, "event": "Gemini battery in BMW iX prototype (June) - 608 mile range"},
        {"year": 2022, "event": "Tesla Model S retrofit: 882-mile range"}
      ],
      "products": ["Gemini dual-chemistry battery", "Aries LFP battery"],
      "competitive_advantages": ["882-mile Tesla retrofit demo", "$1.6B investment", "BMW partnership", "$236.6M Michigan support"],
      "risk_factors": ["Early stage technology", "High capital needs"],
      "confidence_score": 0.96
    },
    {
      "id": 106,
      "name": "Ascend Elements",
      "headquarters": "Westborough, Massachusetts",
      "founded": 2015,
      "technology": "Hydro-to-Cathode direct precursor synthesis",
      "stage": "Commercial (30K+ MT/year)",
      "capacity_target": {"2025": "60K MT/year"},
      "employees": 400,
      "facilities": [
        {"name": "pCAM Pilot", "location": "Westborough, MA", "status": "Operating"},
        {"name": "Apex 1", "location": "Hopkinsville, KY", "capacity": "30K MT/year", "status": "Operating"},
        {"name": "Georgia Expansion", "location": "Georgia", "status": "Under construction"}
      ],
      "funding": {
        "total_raised": "$700M+",
        "latest_round": "Series D - $542M (September 2023)",
        "doe_bil_grants": "$480M total ($316M pCAM active, $164M CAM canceled by mutual agreement)",
        "additional_federal": "$125M (graphite extraction with Orbia)"
      },
      "products": ["Engineered cathode active materials (NMC, LFP) from black mass"],
      "customers": ["GM", "Honda", "Stellantis"],
      "competitive_advantages": ["$480M DOE grants", "30K MT/year capacity", "GM/Honda/Stellantis customers", "Hydro-to-Cathode IP"],
      "risk_factors": ["$164M CAM grant canceled", "Dependent on EV battery scrap volume"],
      "confidence_score": 0.95
    },
    {
      "id": 107,
      "name": "24M Technologies",
      "headquarters": "Cambridge, Massachusetts",
      "founded": 2010,
      "technology": "SemiSolid lithium-ion electrode manufacturing",
      "stage": "Technology licensing",
      "business_model": "Platform licensing to manufacturers",
      "employees": 150,
      "funding": {
        "total_raised": "$500M (across 11 rounds)"
      },
      "licensees": ["Kyocera (Japan - Enerezza residential ESS)", "Lucas TVS (India)", "FREYR Battery (US/Norway)"],
      "awards": ["2024 Technology Award from Electrochemical Society of Japan (with Kyocera)"],
      "features": ["Simplified manufacturing", "Lower CapEx vs traditional", "Thicker electrodes"],
      "competitive_advantages": ["Licensing model = capital efficient", "Kyocera validation", "$500M funding"],
      "risk_factors": ["Dependent on licensee success", "Technology adoption rate"],
      "confidence_score": 0.96
    },
    {
      "id": 108,
      "name": "Ionic Materials",
      "headquarters": "Woburn, Massachusetts",
      "founded": 2011,
      "technology": "Solid-state polymer electrolyte (room temperature)",
      "stage": "R&D / pilot",
      "employees": 70,
      "technical_staff": 28,
      "funding": {
        "series_c": "$65M (February 2018)",
        "investors": ["Renault", "Total Energy", "Nissan", "Mitsubishi", "Dyson", "Samsung"],
        "arpa_e": "Multiple grants (IONICS program, SCALEUP)"
      },
      "achievement": "Highest lithium-conducting solid-state polymer at room temperature",
      "competitive_advantages": ["Room temperature operation", "Polymer safety", "Strategic investors (Renault, Nissan, Samsung)"],
      "risk_factors": ["Early stage", "Commercialization timeline unclear"],
      "confidence_score": 0.94
    },
    {
      "id": 109,
      "name": "Natron Energy",
      "headquarters": "Santa Clara, California (former)",
      "founded": 2012,
      "technology": "Prussian blue sodium-ion batteries",
      "stage": "CEASED OPERATIONS (September 2025)",
      "capacity_planned": "600 MW annual (Holland, MI)",
      "facility_former": "Holland, Michigan (former LG Chem site, opened 2024)",
      "future_project_canceled": "$1.4B North Carolina factory (24 GWh) - canceled",
      "products": ["Blue (sodium-ion) batteries for power applications"],
      "features": ["50,000+ cycle life", "Fast charging", "No lithium/cobalt"],
      "applications": ["Data centers", "EV fast charging", "Forklifts"],
      "status": "Operations ceased September 2025",
      "competitive_advantages": "None (ceased operations)",
      "risk_factors": "Company failed",
      "confidence_score": 0.93
    },
    {
      "id": 110,
      "name": "Electriq Power",
      "headquarters": "San Carlos, California",
      "founded": null,
      "technology": "PowerPod 2 (lithium iron phosphate residential/commercial storage)",
      "stage": "Commercial",
      "funding": {
        "seed": "$6M (2018)",
        "equity": "$3M (2020)",
        "deal_2023": "~$300M"
      },
      "programs": [
        {"name": "Parlier, CA", "scope": "4,000+ homeowners"},
        {"name": "Santa Barbara", "type": "Virtual power plant"}
      ],
      "markets": ["California (SGIP)", "Expanding to New England"],
      "competitive_advantages": ["4,000+ homes deployed", "VPP capability", "$300M deal (2023)"],
      "risk_factors": ["Residential market headwinds", "Limited geographic presence"],
      "confidence_score": 0.92
    },
    {
      "id": 111,
      "name": "Clarios",
      "headquarters": "Glendale, Wisconsin",
      "founded": null,
      "ownership": "Brookfield Business Partners (acquired 2019 for $13.2B)",
      "technology": "Lead-acid batteries (SLI, EFB, AGM)",
      "stage": "Commercial scaled (world's largest lead-acid manufacturer)",
      "scale": "150 million batteries/year, powers 1 in 3 vehicles",
      "expansion": "South Carolina AGM component manufacturing",
      "ipo_plans": "Filed but remains private",
      "parent_tickers": "NYSE: BBU (Brookfield Business Partners), NYSE/TSX: BBUC (Brookfield Business Corporation)",
      "competitive_advantages": ["World's largest lead-acid producer", "150M batteries/year", "Brookfield backing"],
      "risk_factors": ["EV transition threat to lead-acid", "Commodity business"],
      "confidence_score": 0.97
    },
    {
      "id": 112,
      "name": "Lyten",
      "headquarters": "San Leandro, California",
      "founded": null,
      "technology": "Lithium-sulfur batteries",
      "stage": "Development",
      "acquisition": {
        "company": "Cuberg facilities",
        "from": "Northvolt",
        "date": "November 2024",
        "purpose": "Convert to lithium-sulfur battery manufacturing"
      },
      "cuberg_history": {
        "founded": 2015,
        "original_tech": "Lithium-metal battery with liquid electrolyte",
        "acquired_by_northvolt": 2021,
        "northvolt_closed": 2024,
        "prior_customers": ["Boeing", "BETA Technologies", "Ampaire", "VoltAero"]
      },
      "competitive_advantages": ["Lithium-sulfur potential (higher energy density)", "Cuberg production facility"],
      "risk_factors": ["Lithium-sulfur unproven commercially", "Northvolt closure = execution risk"],
      "confidence_score": 0.91
    },
    {
      "id": 113,
      "name": "Prieto Battery",
      "headquarters": "Colorado (inferred)",
      "founded": null,
      "sec_status": "EDGAR entity (CIK: 0001472830)",
      "sic_code": "3691 (Storage Batteries)",
      "information": "Limited public information",
      "competitive_advantages": "Unknown",
      "risk_factors": "Minimal public disclosure",
      "confidence_score": 0.85
    },
    {
      "id": 114,
      "name": "Invinity Energy Systems",
      "ticker_lse": "IES",
      "exchange": "London Stock Exchange",
      "headquarters": null,
      "technology": "Vanadium flow battery",
      "stage": "Commercial",
      "us_presence": "Projects and installations in North America",
      "competitive_advantages": ["Vanadium flow technology", "Long duration storage"],
      "risk_factors": ["Energy density", "Vanadium supply/cost"],
      "confidence_score": 0.92
    },
    {
      "id": 115,
      "name": "Duracell",
      "headquarters": "United States",
      "founded": null,
      "ownership": "Berkshire Hathaway (acquired from P&G, 2014)",
      "technology": "Primary alkaline batteries",
      "stage": "Commercial scaled",
      "us_manufacturing": "Yes (multiple facilities)",
      "sic_code": "3692",
      "competitive_advantages": ["Berkshire backing", "Brand recognition", "Consumer market leader"],
      "risk_factors": ["Rechargeable battery competition", "Commodity market"],
      "confidence_score": 0.97
    },
    {
      "id": 116,
      "name": "Crown Battery",
      "headquarters": "Fremont, Ohio",
      "founded": null,
      "ownership": "Private, family-owned",
      "technology": "Lead-acid batteries (deep cycle, industrial)",
      "stage": "Commercial",
      "competitive_advantages": ["Deep cycle specialization", "Industrial focus"],
      "risk_factors": ["Lead-acid market maturity", "Private = limited disclosure"],
      "confidence_score": 0.90
    },
    {
      "id": 117,
      "name": "East Penn Manufacturing",
      "headquarters": "Lyon Station, Pennsylvania",
      "founded": null,
      "ownership": "Private, employee-owned",
      "technology": "Lead-acid batteries (automotive, industrial, specialty)",
      "stage": "Commercial scaled (one of largest US battery manufacturers)",
      "brands": ["Deka"],
      "competitive_advantages": ["Employee ownership", "Scale", "Deka brand"],
      "risk_factors": ["Lead-acid transition risk", "EV impact"],
      "confidence_score": 0.92
    },
    {
      "id": 118,
      "name": "Trojan Battery Company",
      "headquarters": "Santa Fe Springs, California",
      "founded": null,
      "ownership": "Private",
      "technology": "Deep-cycle batteries (lead-acid, AGM, gel, lithium)",
      "stage": "Commercial",
      "markets": ["Golf carts", "Floor machines", "Renewable energy"],
      "acquisition": {
        "company": "C&D Technologies",
        "date": 2017
      },
      "competitive_advantages": ["Deep-cycle specialization", "Multi-chemistry", "C&D acquisition"],
      "risk_factors": ["Golf cart market niche", "Lithium competition"],
      "confidence_score": 0.91
    },
    {
      "id": 119,
      "name": "Exide Technologies",
      "headquarters": "Milton, Georgia",
      "founded": null,
      "technology": "Lead-acid batteries (automotive, industrial)",
      "stage": "Reorganized (emerged from bankruptcy 2020)",
      "status": "Post-bankruptcy restructuring",
      "competitive_advantages": ["Automotive aftermarket", "Industrial applications"],
      "risk_factors": ["Bankruptcy history", "Lead-acid decline"],
      "confidence_score": 0.87
    },
    {
      "id": 120,
      "name": "Volta Energy Technologies",
      "headquarters": null,
      "type": "Investment fund / venture capital (NOT a battery manufacturer)",
      "focus": "Battery and energy storage technology companies",
      "stage": "Private investment fund",
      "role": "Identifies and invests in battery/energy storage startups",
      "competitive_advantages": "Strategic VC focus on batteries",
      "risk_factors": "Not a manufacturer",
      "confidence_score": 0.95
    }
  ],
  "jointVentures": [
    {
      "id": 201,
      "name": "Ultium Cells LLC",
      "partners": ["General Motors", "LG Energy Solution"],
      "ownership": "50/50",
      "headquarters": "Warren, Michigan",
      "founded": 2019,
      "technology": "NCMA and LFP battery cells",
      "stage": "Production",
      "total_capacity_gwh": 130,
      "facilities": [
        {"name": "Ultium Warren", "location": "Warren, OH", "capacity_gwh": 41, "status": "Operating (September 2022)"},
        {"name": "Ultium Spring Hill", "location": "Spring Hill, TN", "capacity_gwh": 50, "status": "Operating (March 2024), converting to LFP by 2027"},
        {"name": "Ultium Lansing", "location": "Lansing, MI", "capacity_gwh": 41, "status": "Planned"}
      ],
      "employees": 3500,
      "jobs_total": "6,000 construction, 5,100 operations across 3 plants",
      "investment": "$7B total ($2.3B Ohio, $2.3B Tennessee, $2.6B Michigan)",
      "products": ["Pouch cells for GM EVs", "LFP cells for entry models"],
      "competitive_advantages": ["130 GWh capacity", "GM captive demand", "LFP conversion (Spring Hill)"],
      "risk_factors": ["GM EV sales dependent", "LFP competition from China"],
      "confidence_score": 0.99
    },
    {
      "id": 202,
      "name": "BlueOval SK",
      "partners": ["Ford Motor Company", "SK On"],
      "ownership": "50/50",
      "headquarters": "Glendale, Kentucky",
      "founded": 2021,
      "technology": "Li-ion and LFP battery cells",
      "stage": "Production (Kentucky 1), Construction paused (Kentucky 2, Tennessee)",
      "total_capacity_gwh": 130,
      "facilities": [
        {"name": "Kentucky Battery Park 1", "location": "Glendale, KY", "capacity_gwh": 43, "status": "Production (August 2025)"},
        {"name": "Kentucky Battery Park 2", "location": "Glendale, KY", "capacity_gwh": 43, "status": "Construction paused"},
        {"name": "BlueOval City", "location": "Stanton, TN", "capacity_gwh": 43, "status": "Construction paused"},
        {"name": "BlueOval Battery Park Michigan", "location": "Michigan", "capacity_gwh": null, "technology": "LFP", "investment": "$3B"}
      ],
      "employees": 5000,
      "jobs_total": 11000,
      "investment": "$11.4B total (Kentucky + Tennessee)",
      "doe_loan": "$9.63B (closed December 2024)",
      "products": ["Li-ion cells for F-150 Lightning", "Mustang Mach-E", "Future Ford EVs"],
      "competitive_advantages": ["$9.63B DOE loan (largest ever)", "Ford captive demand", "Kentucky 1 operational"],
      "risk_factors": ["Kentucky 2 + Tennessee paused", "Ford EV demand uncertainty"],
      "confidence_score": 0.98
    },
    {
      "id": 203,
      "name": "StarPlus Energy LLC",
      "partners": ["Stellantis", "Samsung SDI"],
      "ownership": "50/50",
      "headquarters": "Kokomo, Indiana",
      "founded": 2022,
      "technology": "Li-ion battery cells",
      "stage": "Under construction",
      "total_capacity_gwh": 67,
      "facilities": [
        {"name": "Kokomo Plant 1", "location": "Kokomo, IN", "capacity_gwh": 33, "status": "2025 start"},
        {"name": "Kokomo Plant 2", "location": "Kokomo, IN", "capacity_gwh": 34, "status": "2027 start"}
      ],
      "employees": 2800,
      "investment": "$6.3B total ($3.2B first plant + additional for second)",
      "doe_loan": "$7.54B (finalized December 2024)",
      "annual_ev_production": "300,000 EVs (Hyundai, Kia, Genesis)",
      "products": ["Cells for Stellantis EVs (Jeep, Ram, Dodge)"],
      "competitive_advantages": ["$7.54B DOE loan", "67 GWh capacity", "Stellantis + Hyundai/Kia demand"],
      "risk_factors": ["Under construction", "Stellantis EV timeline", "2025/2027 start dates"],
      "confidence_score": 0.98
    },
    {
      "id": 204,
      "name": "Panasonic Energy (North America)",
      "partners": ["Panasonic Holdings", "Tesla (partnership)"],
      "headquarters": "De Soto, Kansas",
      "founded": 2014,
      "technology": "2170 and 4680 cylindrical cells",
      "stage": "Production",
      "total_capacity_gwh": 140,
      "facilities": [
        {"name": "Gigafactory Nevada", "location": "Sparks, NV", "capacity_gwh": 100, "status": "Operating (2017)", "products": ["2170 cells", "4680 cells (pilot)"]},
        {"name": "De Soto Factory", "location": "De Soto, KS", "capacity_gwh": 30, "status": "Operating (July 2025)", "products": ["2170 cells"]},
        {"name": "Oklahoma Expansion", "location": "Oklahoma", "capacity_gwh": 10, "status": "Planned"}
      ],
      "employees": 4500,
      "jobs_kansas": "4,000+",
      "investment": "$7B total ($4B Kansas)",
      "products": ["2170 cells (Tesla Model 3/Y)", "4680 cells (Cybertruck pilot)"],
      "competitive_advantages": ["140 GWh capacity", "Tesla partnership", "Multi-customer (Kansas)", "Operational facilities"],
      "risk_factors": ["Tesla exclusivity (Nevada)", "4680 production challenges"],
      "confidence_score": 0.99
    },
    {
      "id": 205,
      "name": "SK Battery America (SK On)",
      "parent": "SK Innovation (South Korea)",
      "headquarters": "Commerce, Georgia",
      "founded": null,
      "technology": "Lithium-ion battery cells",
      "stage": "Production",
      "total_us_capacity_gwh": 180,
      "facilities": [
        {"name": "Commerce Plant", "location": "Commerce, GA", "capacity_gwh": 22, "status": "Operational (2022)", "investment": "$2.6B", "jobs": "3,000+"}
      ],
      "joint_ventures": [
        {"partner": "Hyundai", "location": "Bartow County, GA", "investment": "$5B", "ownership": "50/50", "production": "300K EVs/year by H2 2025"},
        {"partner": "Ford", "jv_name": "BlueOval SK", "plants": "2 Kentucky + 1 Tennessee"}
      ],
      "competitive_advantages": ["180+ GWh US capacity", "Hyundai partnership", "Ford partnership", "Georgia operational"],
      "risk_factors": ["Dependent on Hyundai/Ford EV sales", "Korean parent exposure"],
      "confidence_score": 0.97
    },
    {
      "id": 206,
      "name": "Ford-CATL Partnership",
      "partners": ["Ford Motor Company (100% ownership)", "CATL (technology license)"],
      "ownership": "Ford 100%, CATL technology license",
      "headquarters": "Marshall, Michigan",
      "founded": null,
      "technology": "Lithium iron phosphate (LFP)",
      "stage": "Under construction (60% complete as of June 2025)",
      "capacity_gwh": 20,
      "capacity_original": "35 GWh (reduced)",
      "facility": "Marshall, Michigan",
      "investment": "$2B (reduced from $3.5B)",
      "jobs": 1700,
      "jobs_original": "2,500 (reduced)",
      "expected_opening": 2026,
      "controversy": "Political/legal challenges re: Chinese technology licensing",
      "competitive_advantages": ["CATL LFP technology", "Ford 100% ownership", "20 GWh capacity"],
      "risk_factors": ["Political opposition", "Chinese tech licensing concerns", "Reduced scope (from 35 to 20 GWh)"],
      "confidence_score": 0.96
    },
    {
      "id": 207,
      "name": "Gotion High-Tech (US Subsidiary)",
      "parent": "Gotion High-Tech (China, 30% VW ownership)",
      "us_headquarters": "Fremont, California",
      "founded": null,
      "technology": "Lithium-ion battery cells",
      "stage": "Under construction (Illinois progressing, Michigan facing opposition)",
      "facilities": [
        {"name": "Manteno Plant", "location": "Illinois (former Kmart distribution center)", "capacity_gwh": 50, "breakdown": "40 GWh cells + 10 GWh packs", "investment": "$2B", "jobs": 2600, "state_incentives": "$536M", "status": "Progressing"},
        {"name": "Big Rapids", "location": "Michigan", "investment": "$2.3B", "product": "Battery materials", "status": "Facing delays/opposition"}
      ],
      "competitive_advantages": ["50 GWh Illinois capacity", "VW 30% ownership", "$536M Illinois incentives"],
      "risk_factors": ["Michigan legal/political opposition", "Chinese ownership concerns", "Permitting delays"],
      "confidence_score": 0.93
    },
    {
      "id": 208,
      "name": "LG Energy Solution (US Operations)",
      "parent": "LG Energy Solution (Korea: 373220)",
      "us_headquarters": null,
      "founded": 2020,
      "technology": "Lithium-ion and LFP batteries",
      "stage": "Production",
      "total_us_capacity_gwh": "40+ GWh (direct facilities)",
      "facilities": [
        {"name": "Holland Plant", "location": "Michigan", "status": "Operational"},
        {"name": "Queen Creek Plant", "location": "Arizona", "status": "Operational"}
      ],
      "joint_ventures": ["Ultium Cells (with GM)", "Others"],
      "tesla_contract": "$4.3B for US-built LFP batteries (July 2024)",
      "competitive_advantages": ["Ultium JV with GM", "$4.3B Tesla contract", "Multiple US facilities"],
      "risk_factors": ["Competition from Chinese LFP", "GM EV demand"],
      "confidence_score": 0.98
    },
    {
      "id": 209,
      "name": "Samsung SDI (US Operations)",
      "parent": "Samsung SDI (Korea: 006400)",
      "us_presence": "Via StarPlus Energy JV",
      "joint_venture": "StarPlus Energy (with Stellantis) - See ID 203",
      "technology": "Lithium-ion battery cells",
      "stage": "Under construction (via StarPlus)",
      "competitive_advantages": ["$7.54B DOE loan (StarPlus)", "Stellantis partnership"],
      "risk_factors": ["Dependent on StarPlus JV success"],
      "confidence_score": 0.98
    },
    {
      "id": 210,
      "name": "Kyocera Corporation (US Connection)",
      "parent": "Kyocera Corporation (Tokyo: 6971)",
      "us_connection": "24M Technologies licensing partner",
      "technology": "SemiSolid lithium-ion (licensed from 24M)",
      "stage": "Commercial",
      "product": "Enerezza residential energy storage system",
      "production_capacity": "20,000 units annual (doubling by FY2026)",
      "investment": "JPY 10 billion for new production line",
      "competitive_advantages": ["24M SemiSolid technology", "JPY 10B investment", "Residential ESS focus"],
      "risk_factors": ["Japan-based production", "US market penetration"],
      "confidence_score": 0.95
    }
  ],
  "summary": {
    "total_companies": 62,
    "public_companies": 25,
    "private_major_funding": 20,
    "joint_ventures": 10,
    "subsidiaries": 7,
    "total_capacity_gwh": 850,
    "capacity_2030_target_gwh": 1500,
    "total_investment": "$198B",
    "battery_specific_investment": "$48.3B",
    "jobs_created": 62700,
    "jobs_projected_2027": 100000,
    "doe_loans_committed": "$20.5B+",
    "top_doe_loans": [
      {"company": "BlueOval SK", "amount": "$9.63B"},
      {"company": "StarPlus Energy", "amount": "$7.54B"},
      {"company": "Redwood Materials", "amount": "$2.0B"},
      {"company": "Li-Cycle", "amount": "$375M"},
      {"company": "Eos Energy", "amount": "$303.5M"}
    ]
  }
}
